androcli
